aegis/__init__.py
aegis/__main__.py
aegis/ecosystem.py
aegis/panconfiguration.py
aegis/help/container.py
aegis/modules/environment.py
aegis/modules/gstruc.py
aegis/modules/interpreter.py
aegis/modules/overshoot.py
aegis/modules/phenomap.py
aegis/modules/popgenstats.py
aegis/modules/population.py
aegis/modules/recorder.py
aegis/modules/reproducer.py
aegis/modules/season.py
aegis/modules/trait.py
aegis/parameters/default.yml
aegis/parameters/param.py
aegis/parameters/validate.py
aegis/visor/callbacks.py
aegis/visor/callbacks_config.py
aegis/visor/callbacks_plot.py
aegis/visor/callbacks_results.py
aegis/visor/funcs.py
aegis/visor/layout.py
aegis/visor/static.py
aegis/visor/visor.py
aegis/visor/assets/Inter.ttf
aegis/visor/assets/Quicksand.ttf
aegis/visor/assets/favicon.ico
aegis/visor/assets/list.svg
aegis/visor/assets/plot.svg
aegis/visor/assets/sim.svg
aegis/visor/assets/styles.css
aegis_sim-2.3.0.dist-info/LICENSE
aegis_sim-2.3.0.dist-info/METADATA
aegis_sim-2.3.0.dist-info/WHEEL
aegis_sim-2.3.0.dist-info/entry_points.txt
aegis_sim-2.3.0.dist-info/top_level.txt
aegis_sim-2.3.0.dist-info/RECORD
