Metadata-Version: 2.1
Name: aegis-sim
Version: 2.3.0
Summary: Numerical model for life history evolution of age-structured populations
Home-page: https://github.com/valenzano-lab/aegis
Author: Martin Bagic, Dario Valenzano
Author-email: martin.bagic@outlook.com, Dario.Valenzano@leibniz-fli.de
Requires-Python: >=3.6
License-File: LICENSE
Requires-Dist: numpy
Requires-Dist: pandas
Requires-Dist: PyYAML
Requires-Dist: pyarrow
Requires-Dist: platformdirs
Requires-Dist: dash
Provides-Extra: dev
Requires-Dist: pytest ==6.2.4 ; extra == 'dev'
Requires-Dist: flake8 ; extra == 'dev'
Requires-Dist: black ; extra == 'dev'
